CITATION.txt
LICENSE
MANIFEST.in
README.rst
THANKS.txt
VERSION
ez_setup.py
setup.py
doc/.buildinfo
doc/about.html
doc/genindex.html
doc/index.html
doc/objects.inv
doc/py-modindex.html
doc/search.html
doc/searchindex.js
doc/support.html
doc/_downloads/ETE.pdf
doc/_downloads/apaf.xml
doc/_downloads/face_grid.py
doc/_downloads/nexml_annotated_trees.py
doc/_downloads/nexml_from_scratch.py
doc/_downloads/nexml_parser.py
doc/_downloads/phyloxml_from_scratch.py
doc/_downloads/phyloxml_parser.py
doc/_downloads/species_aware_phylogenies.py
doc/_downloads/tolweb.xml
doc/_downloads/trees.xml
doc/_images/M2_curve.png
doc/_images/M2_default.png
doc/_images/M2_sticks.png
doc/_images/M2_super_profesional.png
doc/_images/barcharts.png
doc/_images/bubble_map.png
doc/_images/bubbles_validation.png
doc/_images/face_borders.png
doc/_images/face_positions.png
doc/_images/fb_clean.png
doc/_images/fb_default.png
doc/_images/float_piechart.png
doc/_images/img_faces.png
doc/_images/item_faces.png
doc/_images/node_background.png
doc/_images/node_style.png
doc/_images/node_style_red_and_blue_nodes.png
doc/_images/node_style_red_nodes.png
doc/_images/phylotree.png
doc/_images/profile_faces.png
doc/_images/rotated_faces.png
doc/_images/rotated_tree.png
doc/_images/scale_x.png
doc/_images/scale_y.png
doc/_images/semi_circular_tree.png
doc/_images/seq_motif_faces.png
doc/_images/seqmotif.png
doc/_images/show_info.png
doc/_images/svg_colors.png
doc/_images/tree_faces.png
doc/_images/treeko_logo.png
doc/_sources/about.txt
doc/_sources/index.txt
doc/_sources/support.txt
doc/_sources/changelog/changelog2.1.txt
doc/_sources/changelog/changelog2.2.txt
doc/_sources/changelog/changelog2.3.txt
doc/_sources/changelog/index.txt
doc/_sources/faqs/index.txt
doc/_sources/reference/index.txt
doc/_sources/reference/reference_clustering.txt
doc/_sources/reference/reference_evoltree.txt
doc/_sources/reference/reference_ncbi.txt
doc/_sources/reference/reference_nexml.txt
doc/_sources/reference/reference_phylo.txt
ete2.egg-info/PKG-INFO
ete2.egg-info/SOURCES.txt
ete2.egg-info/dependency_links.txt
ete2.egg-info/entry_points.txt
ete2.egg-info/top_level.txt
