Metadata-Version: 1.1
Name: ete2
Version: 2.3.9
Summary: A Python Environment for (phylogenetic) Tree Exploration
Home-page: http://etetoolkit.org
Author: Jaime Huerta-Cepas
Author-email: jhcepas@gmail.com
License: GPLv3
Download-URL: http://etetoolkit.org/static/releases/ete2/
Keywords: Tree handling,manipulation,analysis and visualization
Platform: OS Independent
Classifier: Development Status :: 6 - Mature
Classifier: Environment :: Console
Classifier: Environment :: X11 Applications :: Qt
Classifier: Intended Audience :: Developers
Classifier: Intended Audience :: Other Audience
Classifier: Intended Audience :: Science/Research
Classifier: License :: OSI Approved :: GNU General Public License (GPL)
Classifier: Natural Language :: English
Classifier: Operating System :: MacOS
Classifier: Operating System :: Microsoft :: Windows
Classifier: Operating System :: POSIX :: Linux
Classifier: Programming Language :: Python
Classifier: Topic :: Scientific/Engineering :: Bio-Informatics
Classifier: Topic :: Scientific/Engineering :: Visualization
Classifier: Topic :: Software Development :: Libraries :: Python Modules
Provides: ete2
